lingkar33423319/__init__.py
lingkar33423319/lingkaran.py
lingkar33423319-1.0.dist-info/LICENSE
lingkar33423319-1.0.dist-info/METADATA
lingkar33423319-1.0.dist-info/WHEEL
lingkar33423319-1.0.dist-info/top_level.txt
lingkar33423319-1.0.dist-info/RECORD
