Metadata-Version: 2.1
Name: lingkar33423319
Version: 1.0
Summary: hitung luas lingkaran
Home-page: https://github.com/iqbull2244/lingkaran.git
Author: iqbal
Author-email: <rafiiqbal2407@gmail.com>
License: MIT
Keywords: lingkaran,luas
Classifier: Development Status :: 1 - Planning
License-File: LICENSE
